nomiden/__init__.py
nomiden/kk.py
nomiden/nik.py
nomiden/reader.py
nomiden/data/regcode.csv
nomiden/data/regioncode.csv
nomiden-0.0.7.dist-info/LICENSE
nomiden-0.0.7.dist-info/METADATA
nomiden-0.0.7.dist-info/WHEEL
nomiden-0.0.7.dist-info/top_level.txt
nomiden-0.0.7.dist-info/RECORD
