Metadata-Version: 2.1
Name: nomiden
Version: 0.0.7
Summary: A Python package to extract information from Indonesian ID Number (NIK, KK)
Home-page: https://github.com/divakartika/nomiden
Author: Diva K
Author-email: diva@algorit.ma
License: MIT
Classifier: License :: OSI Approved :: MIT License
Classifier: Programming Language :: Python :: 3
Classifier: Operating System :: OS Independent
Requires-Python: >=3.7
License-File: LICENSE
Requires-Dist: pandas
